gene_trajectory/__init__.py
gene_trajectory/add_gene_bin_score.py
gene_trajectory/coarse_grain.py
gene_trajectory/compute_gene_distance_cmd.py
gene_trajectory/diffusion_map.py
gene_trajectory/extract_gene_trajectory.py
gene_trajectory/gene_distance_shared.py
gene_trajectory/get_graph_distance.py
gene_trajectory/run_dm.py
gene_trajectory/plot/__init__.py
gene_trajectory/plot/gene_trajectory_plots.py
gene_trajectory/util/__init__.py
gene_trajectory/util/download_file.py
gene_trajectory/util/input_validation.py
gene_trajectory/util/shared_array.py
gene_trajectory/widgets/__init__.py
gene_trajectory/widgets/extract_gene_trajectory_widget.py
gene_trajectory-1.0.4.dist-info/LICENSE
gene_trajectory-1.0.4.dist-info/WHEEL
gene_trajectory-1.0.4.dist-info/METADATA
gene_trajectory-1.0.4.dist-info/RECORD
