Metadata-Version: 2.1
Name: gene-trajectory
Version: 1.0.4
Summary: Compute gene trajectories
Keywords: Gene trajectory,scRNA-seq
Author-email: Francesco Strino <francesco.strino@pcmgf.com>, Rihao Qu <rihao.qu@yale.edu>
Maintainer-email: Francesco Strino <francesco.strino@pcmgf.com>, Rihao Qu <rihao.qu@yale.edu>
Requires-Python: >=3.9
Classifier: Development Status :: 4 - Beta
Classifier: Programming Language :: Python
Classifier: License :: OSI Approved :: BSD License
Classifier: Intended Audience :: Science/Research
Requires-Dist: igraph>=0.10
Requires-Dist: matplotlib>=3.6
Requires-Dist: numpy>=1.25
Requires-Dist: pandas>=1.5
Requires-Dist: pot>=0.8.2
Requires-Dist: scanpy>=1.9.3
Requires-Dist: scikit-misc>=0.1.3
Requires-Dist: scikit-learn>=0.24
Requires-Dist: scipy>=1.8
Requires-Dist: seaborn>=0.13
Requires-Dist: tqdm>=4.64.1
Requires-Dist: pytest ; extra == "dev"
Requires-Dist: twine ; extra == "dev"
Requires-Dist: ipywidgets>8 ; extra == "widgets"
Requires-Dist: jupyterlab>=4 ; extra == "widgets"
Project-URL: Bug Tracker, https://github.com/KlugerLab/GeneTrajectory-python/issues
Project-URL: Documentation, https://github.com/KlugerLab/GeneTrajectory-python.git
Project-URL: Repository, https://github.com/KlugerLab/GeneTrajectory-python.git
Provides-Extra: dev
Provides-Extra: widgets
